joke_stat_transaction/__init__.py
joke_stat_transaction/__main__.py
joke_stat_transactions-0.1.0.dist-info/METADATA
joke_stat_transactions-0.1.0.dist-info/WHEEL
joke_stat_transactions-0.1.0.dist-info/top_level.txt
joke_stat_transactions-0.1.0.dist-info/RECORD
