Metadata-Version: 2.1
Name: joke_stat_transactions
Version: 0.1.0
Summary: Быстрый анализ данных csv
Author-email: Pablo <p.ergle@edu.centraluniversity.ru>
License: MIT
Requires-Python: >=3.12
Requires-Dist: pandas>=2.2.3
